subrename/__init__.py
subrename/__version__.py
subrename/main.py
subrename/subrename.py
subrename-0.1.0.dist-info/LICENSE
subrename-0.1.0.dist-info/METADATA
subrename-0.1.0.dist-info/WHEEL
subrename-0.1.0.dist-info/entry_points.txt
subrename-0.1.0.dist-info/top_level.txt
subrename-0.1.0.dist-info/RECORD
