Metadata-Version: 2.1
Name: subrename
Version: 0.1.0
Summary: Rename subtitles in batch
Home-page: https://github.com/kevinzg/subrename
Author: Kevin Zúñiga
Author-email: kevin.zun@gmail.com
License: MIT
Platform: UNKNOWN
Classifier: License :: OSI Approved :: MIT License
Classifier: Programming Language :: Python
Classifier: Programming Language :: Python :: 3
Classifier: Programming Language :: Python :: 3.6
Classifier: Programming Language :: Python :: Implementation :: CPython
Classifier: Programming Language :: Python :: Implementation :: PyPy
Requires-Python: >=3.6.0
Requires-Dist: fire
Requires-Dist: colorama
